fairmat_readers_xrd/__init__.py
fairmat_readers_xrd/_version.py
fairmat_readers_xrd/bruker_raw_parser.py
fairmat_readers_xrd/ikz.py
fairmat_readers_xrd/readers.py
fairmat_readers_xrd/utils.py
fairmat_readers_xrd-0.0.8.dist-info/licenses/LICENSE
fairmat_readers_xrd-0.0.8.dist-info/METADATA
fairmat_readers_xrd-0.0.8.dist-info/WHEEL
fairmat_readers_xrd-0.0.8.dist-info/top_level.txt
fairmat_readers_xrd-0.0.8.dist-info/RECORD
