Metadata-Version: 2.4
Name: fairmat-readers-xrd
Version: 0.0.8
Summary: A package containing file readers for XRD raw files.
Author-email: Sarthak Kapoor <sarthak.kapoor@physik.hu-berlin.de>, Hampus Näsström <hampus.naesstroem@physik.hu-berlin.de>, Andrea Albino <andrea.albino@physik.hu-berlin.de>, Sebastian Brückner <sebastian.brueckner@ikz-berlin.de>
License:                                  Apache License
Project-URL: Homepage, https://github.com/FAIRmat-NFDI/readers-xrd
Project-URL: Bug Tracker, https://github.com/FAIRmat-NFDI/readers-xrd/issues
Classifier: Programming Language :: Python :: 3
Classifier: Programming Language :: Python :: 3 :: Only
Classifier: Programming Language :: Python :: 3.9
Classifier: License :: OSI Approved :: Apache Software License
Requires-Python: >=3.8
License-File: LICENSE
Requires-Dist: xmltodict==0.13.0
Requires-Dist: numpy>=1.21.2
Requires-Dist: pint>=0.17
Provides-Extra: dev
Requires-Dist: pytest; extra == "dev"
Requires-Dist: ruff; extra == "dev"
Requires-Dist: pre-commit; extra == "dev"
Requires-Dist: structlog==22.3.0; extra == "dev"
Dynamic: license-file
